LICENSE
MANIFEST.in
README
distribute_setup.py
setup.py
examples/hello-bench.py
examples/hello.py
examples/pyramid-bench.py
examples/verticalstack-bench.py
pypybox2d/__init__.py
pypybox2d/body.py
pypybox2d/broadphase.py
pypybox2d/collision.py
pypybox2d/collision_util.py
pypybox2d/common.py
pypybox2d/contact.py
pypybox2d/contact_manager.py
pypybox2d/contact_util.py
pypybox2d/controllers.py
pypybox2d/distance.py
pypybox2d/dynamictree.py
pypybox2d/fixture.py
pypybox2d/island.py
pypybox2d/settings.py
pypybox2d/shapes.py
pypybox2d/toi.py
pypybox2d/world.py
pypybox2d.egg-info/PKG-INFO
pypybox2d.egg-info/SOURCES.txt
pypybox2d.egg-info/dependency_links.txt
pypybox2d.egg-info/top_level.txt
pypybox2d/src/aabbmodule.c
pypybox2d/src/commonmodule.c
pypybox2d/src/mat22module.c
pypybox2d/src/transform.c
pypybox2d/src/vec2module.c
pypybox2d/joints/__init__.py
pypybox2d/joints/distance.py
pypybox2d/joints/friction.py
pypybox2d/joints/gear.py
pypybox2d/joints/joint.py
pypybox2d/joints/mouse.py
pypybox2d/joints/prismatic.py
pypybox2d/joints/pulley.py
pypybox2d/joints/revolute.py
pypybox2d/joints/rope.py
pypybox2d/joints/weld.py
pypybox2d/joints/wheel.py
pypybox2d/src/aabbmodule.c
pypybox2d/src/common.h
pypybox2d/src/commonmodule.c
pypybox2d/src/mat22module.c
pypybox2d/src/transform.c
pypybox2d/src/vec2module.c
testbed/apply_force.py
testbed/body_types.py
testbed/box_cutter.py
testbed/breakable.py
testbed/bridge.py
testbed/bullet.py
testbed/buoyancy.py
testbed/cantilever.py
testbed/car.py
testbed/chain.py
testbed/character_collision.py
testbed/collision_filtering.py
testbed/collision_processing.py
testbed/confined.py
testbed/distance.py
testbed/edge_shapes.py
testbed/edge_test.py
testbed/framework.py
testbed/friction.py
testbed/gear.py
testbed/gish_tribute.py
testbed/gravity_bridge.py
testbed/one_sided_platform.py
testbed/pinball.py
testbed/profiler.py
testbed/pulley.py
testbed/pyramid.py
testbed/raycast.py
testbed/restitution.py
testbed/ropes.py
testbed/test_empty.py
testbed/theo_jansen.py
testbed/tiles.py
testbed/time_of_impact.py
testbed/vertical_stack.py
testbed/web.py
testbed/runsnakerun/__init__.py
